setup.py
data/__init__.py
docs/conf.py
src/getcf/__init__.py
src/getcf/exception.py
src/getcf/main.py
src/getcf/reverse.py
src/getcf/runner.py
getyourcf-1.0.0.dist-info/METADATA
getyourcf-1.0.0.dist-info/WHEEL
getyourcf-1.0.0.dist-info/licenses/LICENSE
getyourcf-1.0.0.dist-info/RECORD
