Metadata-Version: 2.1
Name: getyourcf
Version: 1.0.0
Summary: A small package to retrieve fiscal code
Project-URL: Homepage, https://github.com/andreasala98/getyourcf
Author-email: Andrea Sala <andrea.sala98@gmail.com>
License-File: LICENSE
Classifier: Operating System :: OS Independent
Classifier: Programming Language :: Python :: 3
Requires-Python: >=3.7
